combustion/__init__.py
combustion/__main__.py
combustion/exceptions.py
combustion/version.py
combustion/data/__init__.py
combustion/data/batch.py
combustion/data/serialize.py
combustion/data/window.py
combustion/lightning/__init__.py
combustion/lightning/callbacks.py
combustion/lightning/mixins.py
combustion/lightning/callbacks/__init__.py
combustion/lightning/callbacks/base.py
combustion/lightning/callbacks/matplotlib.py
combustion/lightning/callbacks/other.py
combustion/lightning/callbacks/tensors.py
combustion/lightning/callbacks/visualization.py
combustion/lightning/metrics/__init__.py
combustion/lightning/metrics/auroc.py
combustion/lightning/metrics/average_precision.py
combustion/lightning/metrics/bbox_metric.py
combustion/lightning/metrics/confidence.py
combustion/lightning/metrics/entropy.py
combustion/models/__init__.py
combustion/models/efficientdet.py
combustion/models/efficientdet_fcos.py
combustion/models/efficientnet.py
combustion/models/mobile_unet.py
combustion/nn/__init__.py
combustion/nn/activations/__init__.py
combustion/nn/activations/hsigmoid.py
combustion/nn/activations/swish.py
combustion/nn/functional/__init__.py
combustion/nn/functional/clamp_normalize.py
combustion/nn/functional/fill_masked.py
combustion/nn/functional/fourier_conv.py
combustion/nn/functional/fourier_filter.py
combustion/nn/functional/polar.py
combustion/nn/loss/__init__.py
combustion/nn/loss/centernet.py
combustion/nn/loss/ciou.py
combustion/nn/loss/fcos.py
combustion/nn/loss/focal.py
combustion/nn/modules/__init__.py
combustion/nn/modules/bifpn.py
combustion/nn/modules/bottleneck.py
combustion/nn/modules/clamp_normalize.py
combustion/nn/modules/conv.py
combustion/nn/modules/dropconnect.py
combustion/nn/modules/dynamic_pad.py
combustion/nn/modules/factorized.py
combustion/nn/modules/fcos.py
combustion/nn/modules/fpn_shared_head.py
combustion/nn/modules/global_attention_upsample.py
combustion/nn/modules/match_shapes.py
combustion/nn/modules/mobilenet.py
combustion-0.1.0.dist-info/LICENSE
combustion-0.1.0.dist-info/METADATA
combustion-0.1.0.dist-info/WHEEL
combustion-0.1.0.dist-info/top_level.txt
combustion-0.1.0.dist-info/RECORD
